ise.py
ISE-0.1.2.dist-info/LICENSE
ISE-0.1.2.dist-info/METADATA
ISE-0.1.2.dist-info/WHEEL
ISE-0.1.2.dist-info/top_level.txt
ISE-0.1.2.dist-info/RECORD
