Metadata-Version: 2.1
Name: ISE
Version: 0.1.2
Summary: Python wrapper for Cisco ISE ERS API
Home-page: https://github.com/falkowich/ise
Maintainer: Andreas Falk
Maintainer-email: falk@sadsloth.net
License: LICENSE.md
Download-URL: https://pypi.python.org/pypi/ise
Platform: UNKNOWN
Requires-Python: >=3.6
Requires-Dist: furl (>=2.1.0)
Requires-Dist: requests (>=2.23.0)
Provides-Extra: test
Requires-Dist: pytest ; extra == 'test'
Requires-Dist: coverage ; extra == 'test'
